ezmsg/simbiophys/__init__.py
ezmsg/simbiophys/__version__.py
ezmsg/simbiophys/cosine_encoder.py
ezmsg/simbiophys/dynamic_colored_noise.py
ezmsg/simbiophys/eeg.py
ezmsg/simbiophys/noise.py
ezmsg/simbiophys/oscillator.py
ezmsg/simbiophys/dnss/__init__.py
ezmsg/simbiophys/dnss/lfp.py
ezmsg/simbiophys/dnss/pattern_match.py
ezmsg/simbiophys/dnss/spike.py
ezmsg/simbiophys/dnss/synth.py
ezmsg/simbiophys/dnss/wfs.py
ezmsg/simbiophys/system/__init__.py
ezmsg/simbiophys/system/velocity2ecephys.py
ezmsg/simbiophys/system/velocity2lfp.py
ezmsg/simbiophys/system/velocity2spike.py
ezmsg/simbiophys/util/__init__.py
ezmsg_simbiophys-1.2.0.dist-info/METADATA
ezmsg_simbiophys-1.2.0.dist-info/WHEEL
ezmsg_simbiophys-1.2.0.dist-info/licenses/LICENSE
ezmsg_simbiophys-1.2.0.dist-info/RECORD
