Metadata-Version: 2.4
Name: ezmsg-simbiophys
Version: 1.2.0
Summary: Signal simulation and synthesis for ezmsg
Author-email: Chadwick Boulay <chadwick.boulay@gmail.com>
License-Expression: MIT
License-File: LICENSE
Requires-Python: >=3.10.15
Requires-Dist: ezmsg-baseproc>=1.2.1
Requires-Dist: ezmsg-event>=0.6.0
Requires-Dist: ezmsg-sigproc>=2.8.0
Requires-Dist: ezmsg>=3.6.0
Requires-Dist: numpy>=1.26.0
Requires-Dist: sparse>=0.17.0
